{
  "wands": [
    {
      "id": "1718657041251",
      "photo": "Green.webp",
      "shuffle": "No",
      "spellCast": "1",
      "castDelay": "0.05",
      "rechargeTime": "0.67",
      "manaMax": "300",
      "manaChargeSpeed": "104",
      "capacity": "7",
      "spread": "-2",
      "spells": [
        "210",
        "173",
        "84",
        "307",
        "235",
        "235",
        "228"
      ]
    },
    {
      "id": "1718659398735",
      "photo": "Purple.webp",
      "shuffle": "No",
      "spellCast": "1",
      "castDelay": "0.27",
      "rechargeTime": "0.67",
      "manaMax": "960",
      "manaChargeSpeed": "390",
      "capacity": "11",
      "spread": "0",
      "spells": [
        "211",
        "174",
        "96",
        "221",
        "22",
        "68",
        "48",
        "106",
        "48",
        "46",
        "46"
      ]
    },
    {
      "id": "1718659489020",
      "photo": "Purple.webp",
      "shuffle": "No",
      "spellCast": "1",
      "castDelay": "0.27",
      "rechargeTime": "0.67",
      "manaMax": "960",
      "manaChargeSpeed": "390",
      "capacity": "10",
      "spread": "0",
      "spells": [
        "211",
        "174",
        "96",
        "221",
        "68",
        "48",
        "106",
        "48",
        "46",
        "46"
      ]
    },
    {
      "id": "1718784257493",
      "photo": "Yellow.webp",
      "shuffle": "No",
      "spellCast": "1",
      "castDelay": "0.28",
      "rechargeTime": "0.53",
      "manaMax": "547",
      "manaChargeSpeed": "320",
      "capacity": "8",
      "spread": "0",
      "spells": [
        "221",
        "59",
        "288",
        "324",
        "324",
        "96",
        "54",
        "319"
      ]
    },
    {
      "id": "1718784968811",
      "photo": "Red.webp",
      "shuffle": "No",
      "spellCast": "1",
      "castDelay": "0.37",
      "rechargeTime": "0.37",
      "manaMax": "600",
      "manaChargeSpeed": "248",
      "capacity": "10",
      "spread": "-2",
      "spells": [
        "221",
        null,
        "360",
        "171",
        "325",
        "178",
        "111",
        "252",
        "209",
        "299"
      ]
    }
  ]
}